Chrono/BuildSCATEEntities.py
Chrono/TimePhraseEntity.py
Chrono/TimePhrase_to_Chrono.py
Chrono/__init__.py
Chrono/chronoEntities.py
Chrono/config.py
Chrono/gold_standard_utils.py
Chrono/referenceToken.py
Chrono/temporalTest.py
Chrono/utils.py
Chrono/w2ny.py
Chrono/ChronoUtils/ML_utils.py
Chrono/ChronoUtils/__init__.py
Chrono/ChronoUtils/filesystem_utils.py
Chrono/ChronoUtils/initialize_chrono.py
Chrono/ChronoUtils/parse_text.py
Chrono/TimePhraseToChrono/AMPM.py
Chrono/TimePhraseToChrono/BeforeAfter.py
Chrono/TimePhraseToChrono/DayOfMonth.py
Chrono/TimePhraseToChrono/DayOfWeek.py
Chrono/TimePhraseToChrono/HourOfDay.py
Chrono/TimePhraseToChrono/Last.py
Chrono/TimePhraseToChrono/MinuteOfHour.py
Chrono/TimePhraseToChrono/Modifier.py
Chrono/TimePhraseToChrono/MonthYear.py
Chrono/TimePhraseToChrono/NthFromStart.py
Chrono/TimePhraseToChrono/NumericDate.py
Chrono/TimePhraseToChrono/PartOfDay.py
Chrono/TimePhraseToChrono/PartOfWeek.py
Chrono/TimePhraseToChrono/PeriodInterval.py
Chrono/TimePhraseToChrono/Season.py
Chrono/TimePhraseToChrono/SecondOfMinute.py
Chrono/TimePhraseToChrono/TextMonthAndDay.py
Chrono/TimePhraseToChrono/TextYear.py
Chrono/TimePhraseToChrono/This.py
Chrono/TimePhraseToChrono/TimeZone.py
Chrono/TimePhraseToChrono/TwentyFourHourTime.py
Chrono/TimePhraseToChrono/__init__.py
Chrono/chronoML/ChronoKeras.py
Chrono/chronoML/DecisionTree.py
Chrono/chronoML/FrequencyRNN.py
Chrono/chronoML/NB_nltk_classifier.py
Chrono/chronoML/RF_classifier.py
Chrono/chronoML/SVM_classifier.py
Chrono/chronoML/__init__.py
Chrono/chronoML/chronoML/ChronoKeras.py
Chrono/chronoML/chronoML/DecisionTree.py
Chrono/chronoML/chronoML/NB_nltk_classifier.py
Chrono/chronoML/chronoML/RF_classifier.py
Chrono/chronoML/chronoML/SVM_classifier.py
Chrono/chronoML/chronoML/__init__.py
Chrono/dictionary/AbrDay.txt
Chrono/dictionary/AbrMonth.txt
Chrono/dictionary/After.txt
Chrono/dictionary/Before.txt
Chrono/dictionary/FullDay.txt
ChronoNLP-3.0.2.dist-info/METADATA
ChronoNLP-3.0.2.dist-info/RECORD
ChronoNLP-3.0.2.dist-info/WHEEL
ChronoNLP-3.0.2.dist-info/top_level.txt
